mlxx/__init__.py
mlxx/array_extensions.py
mlxx-0.3.2.dist-info/METADATA
mlxx-0.3.2.dist-info/WHEEL
mlxx-0.3.2.dist-info/licenses/LICENSE
mlxx-0.3.2.dist-info/RECORD
