Metadata-Version: 2.4
Name: mlxx
Version: 0.3.2
Summary: MLX array supercharged
Project-URL: Repository, https://github.com/ifsheldon/mlxx
Project-URL: Issues, https://github.com/ifsheldon/mlxx/issues
Author-email: ifsheldon <feng.liang@kaust.edu.sa>
License: MIT License
License-File: LICENSE
Keywords: deep learning,mlx
Requires-Python: >=3.10
Requires-Dist: fastcore>=1.8.2
Requires-Dist: mlx>=0.26.0
Provides-Extra: numpy
Requires-Dist: numpy>=2; extra == 'numpy'
